pytest_percent.py
pytest_percent-0.1.2.dist-info/LICENSE
pytest_percent-0.1.2.dist-info/METADATA
pytest_percent-0.1.2.dist-info/WHEEL
pytest_percent-0.1.2.dist-info/entry_points.txt
pytest_percent-0.1.2.dist-info/top_level.txt
pytest_percent-0.1.2.dist-info/RECORD
