Metadata-Version: 2.1
Name: pytest-percent
Version: 0.1.2
Summary: Change the exit code of pytest test sessions when a required percent of tests pass.
Home-page: https://github.com/dillonm197/pytest.percent
Author: Dillon Miller
Author-email: dillon.miller@swiftpage.com
Maintainer: Dillon Miller
Maintainer-email: dillon.miller@swiftpage.com
License: MIT
Platform: UNKNOWN
Classifier: Framework :: Pytest
Classifier: Intended Audience :: Developers
Classifier: Topic :: Software Development :: Testing
Classifier: Programming Language :: Python
Classifier: Programming Language :: Python :: 3.7
Classifier: Operating System :: OS Independent
Classifier: License :: OSI Approved :: MIT License
Requires-Python: >=3.7
Requires-Dist: pytest (>=5.2.0)
